{
  "usersData": [
    {
      "id": 0.7747518473408821,
      "siblings": [
        "olderSister",
        "youngerSister",
        "olderBrother"
      ],
      "firstName": "صحرا",
      "lastName": "طهران",
      "birthDay": "d13",
      "birthMonth": "m10",
      "birthYear": "Y1371",
      "gender": "1",
      "phoneNumber": "01111111111",
      "cellPhoneNumber": "01111111111",
      "city": "alborz",
      "address": "s",
      "numberOfFamilyMember": 1,
      "isTwins": "noTwins",
      "isMarried": "married"
    },
    {
      "id": 0.7775402319879737,
      "siblings": [
        "olderSister",
        "olderBrother"
      ],
      "firstName": "sahra",
      "lastName": "tehrani",
      "birthDay": "d10",
      "birthMonth": "m11",
      "birthYear": "Y1370",
      "gender": "1",
      "phoneNumber": "01111111111",
      "cellPhoneNumber": "01111111111",
      "city": "tabriz",
      "address": "sss",
      "numberOfFamilyMember": 5,
      "isTwins": "noTwins",
      "isMarried": "married"
    },
    {
      "id": 0.07465966457979578,
      "siblings": [
        "olderSister"
      ],
      "firstName": "صحرا",
      "lastName": "آئین دار طهران",
      "birthDay": "d16",
      "birthMonth": "m02",
      "birthYear": "Y1378",
      "gender": "1",
      "phoneNumber": "02123456789",
      "cellPhoneNumber": "09109420978",
      "city": "tehran",
      "address": "اندیشه فاز سه خیابان ولیعصر کوچه سعدی بن بست چهارم پ113",
      "numberOfFamilyMember": 4,
      "isTwins": "noTwins",
      "isMarried": "notMarried"
    }
  ]
}